odoo/addons/avoid_check_balanced_credit_debit/README.rst
odoo/addons/avoid_check_balanced_credit_debit/__init__.py
odoo/addons/avoid_check_balanced_credit_debit/__manifest__.py
odoo/addons/avoid_check_balanced_credit_debit/models/__init__.py
odoo/addons/avoid_check_balanced_credit_debit/models/account_move.py
odoo/addons/avoid_check_balanced_credit_debit/static/description/icon.png
odoo13_addon_avoid_check_balanced_credit_debit-13.0.1.0.0.dist-info/METADATA
odoo13_addon_avoid_check_balanced_credit_debit-13.0.1.0.0.dist-info/WHEEL
odoo13_addon_avoid_check_balanced_credit_debit-13.0.1.0.0.dist-info/top_level.txt
odoo13_addon_avoid_check_balanced_credit_debit-13.0.1.0.0.dist-info/RECORD
